<?xml version="1.0" encoding="UTF-8"?>
<!DOCTYPE suite SYSTEM "https://testng.org/testng-1.0.dtd">
<suite name="Suite">
  <test thread-count="5" name="Test">
    <classes>
      <class name="TestngActivities.DemoTwo"/>
      <class name="TestngActivities.Activity1"/>
      <class name="TestngActivities.Activity2"/>
      <class name="TestngActivities.Activity7"/>
      <class name="TestngActivities.Activity9"/>
      <class name="TestngActivities.DemoOne"/>
      <class name="TestngActivities.Activity3"/>
      <class name="TestngActivities.Activity5"/>
      <class name="activities.Activity6" />

    </classes>
  </test> <!-- Test -->
</suite> <!-- Suite -->
